observa/__init__.py
observa/app.py
observa/local.py
observa/api/__init__.py
observa/api/router.py
observa/api/endpoints/__init__.py
observa/api/endpoints/admin.py
observa/api/endpoints/detectors.py
observa/api/endpoints/runs.py
observa/api/endpoints/sources.py
observa/database/database.py
observa/database/models.py
observa/database/repositories.py
observa/detectors/__init__.py
observa/detectors/excessive.py
observa/detectors/excessive_alerts.py
observa/detectors/frutas_detector.py
observa/detectors/remote_detector.py
observa/framework/__init__.py
observa/framework/base.py
observa/framework/manager.py
observa/framework/orchestrator.py
observa/sources/__init__.py
observa/sources/data_source.py
observa/sources/frutas_source.py
observa/sources/json_source.py
observa_framework-0.1.2.dist-info/METADATA
observa_framework-0.1.2.dist-info/WHEEL
observa_framework-0.1.2.dist-info/top_level.txt
observa_framework-0.1.2.dist-info/RECORD
