Metadata-Version: 2.4
Name: observa-framework
Version: 0.1.2
Summary: A framework for antipattern detection and observability analysis
Author-email: Anderson Almada <almada@crateus.ufc.br>
License: MIT
Project-URL: Homepage, https://github.com/andersonalmada/detect-antipatterns
Requires-Python: >=3.8
Requires-Dist: fastapi
Requires-Dist: sqlalchemy
Requires-Dist: psycopg2-binary
Requires-Dist: httpx
Requires-Dist: uvicorn
Requires-Dist: dotenv
